tapioca_telegram/__init__.py
tapioca_telegram/resource_mapping.py
tapioca_telegram/tapioca_telegram.py
tapioca_telegram-0.1.dist-info/DESCRIPTION.rst
tapioca_telegram-0.1.dist-info/METADATA
tapioca_telegram-0.1.dist-info/metadata.json
tapioca_telegram-0.1.dist-info/RECORD
tapioca_telegram-0.1.dist-info/top_level.txt
tapioca_telegram-0.1.dist-info/WHEEL
