Metadata-Version: 2.0
Name: tapioca-telegram
Version: 0.1
Summary: Telegram API wrapper using tapioca
Home-page: https://github.com/rougeth/tapioca-telegram
Author: Marco Rougeth
Author-email: marco@rougeth.com
License: MIT
Keywords: telegram-api-bot
Platform: UNKNOWN
Classifier: Development Status :: 5 - Production/Stable
Classifier: Intended Audience :: Developers
Classifier: License :: OSI Approved :: MIT License
Classifier: Natural Language :: English
Classifier: Programming Language :: Python :: 2
Classifier: Programming Language :: Python :: 2.7
Classifier: Programming Language :: Python :: 3
Classifier: Programming Language :: Python :: 3.1
Classifier: Programming Language :: Python :: 3.2
Classifier: Programming Language :: Python :: 3.3
Classifier: Programming Language :: Python :: 3.4
Requires-Dist: tapioca-wrapper (<0.7.0)
